node/__init__.py
node/compositor.py
node/expression.py
node/group.py
node/internal.py
node/properties.py
node/shader.py
node/texture.py
node/util.py
node/value.py
node_expressions-0.1.2.dist-info/LICENSE
node_expressions-0.1.2.dist-info/METADATA
node_expressions-0.1.2.dist-info/WHEEL
node_expressions-0.1.2.dist-info/top_level.txt
node_expressions-0.1.2.dist-info/RECORD
